djangohelper/__init__.py
djangohelper/__main__.py
djangohelper/common.py
djangohelper/number_tool.py
djangohelper/project2lines.py
djangohelper/util.py
djangohelper/auth/__init__.py
djangohelper/auth/hasher.py
djangohelper/contrib/__init__.py
djangohelper/contrib/developer/__init__.py
djangohelper/contrib/developer/admin.py
djangohelper/contrib/developer/apps.py
djangohelper/contrib/developer/models.py
djangohelper/contrib/developer/tests.py
djangohelper/contrib/developer/views.py
djangohelper/contrib/friendlink/__init__.py
djangohelper/contrib/friendlink/admin.py
djangohelper/contrib/friendlink/apps.py
djangohelper/contrib/friendlink/models.py
djangohelper/contrib/friendlink/tests.py
djangohelper/contrib/friendlink/views.py
djangohelper/contrib/friendlink/migrations/0001_initial.py
djangohelper/contrib/friendlink/migrations/__init__.py
djangohelper/contrib/snowlandauth/__init__.py
djangohelper/contrib/snowlandauth/admin.py
djangohelper/contrib/snowlandauth/apps.py
djangohelper/contrib/snowlandauth/models.py
djangohelper/contrib/snowlandauth/tests.py
djangohelper/contrib/snowlandauth/views.py
djangohelper/contrib/snowlandauth/migrations/__init__.py
djangohelper/db/__init__.py
djangohelper/db/utils.py
djangohelper/db/models/__init__.py
djangohelper/db/models/_base.py
djangohelper/permissions/__init__.py
djangohelper/permissions/_permissions.py
djangohelper/requests/__init__.py
djangohelper/requests/requests_helper.py
djangohelper/responses/__init__.py
djangohelper/responses/_responses.py
djangohelper/utils/__init__.py
djangohelper/utils/crypto.py
djangohelper/utils/regex_helper.py
djangohelper/viewhelper/__init__.py
djangohelper/viewhelper/paginator.py
djangohelper/views/__init__.py
djangohelper/viewsets/__init__.py
djangohelper/viewsets/_viewsets.py
snowland_djangohelper-0.1.1.dist-info/DESCRIPTION.rst
snowland_djangohelper-0.1.1.dist-info/METADATA
snowland_djangohelper-0.1.1.dist-info/RECORD
snowland_djangohelper-0.1.1.dist-info/WHEEL
snowland_djangohelper-0.1.1.dist-info/metadata.json
snowland_djangohelper-0.1.1.dist-info/top_level.txt
